RGBtoGrayscale.v
module RGBtoGrayscale(Red, Green, Blue, RedOut, GreenOut, BlueOut, clk);
    input [0:7] Red, Green, Blue;
    input clk;
    output reg [0:7] RedOut, GreenOut, BlueOut;

    reg [0:7]GrayValue;

    always @(negedge clk)
    begin
        GrayValue = Red*0.3 + Green*0.59 + Blue*0.11;
        //GrayValue = (Red >> 2) + (Red >> 5) + (Green >> 1) + (Green >> 4) + (Blue >> 4) + (Blue >> 5);
        RedOut <= GrayValue;
        BlueOut <= GrayValue;
        GreenOut <= GrayValue;
    end
endmodule

tb.v
`timescale 1ns/1ns
module tb;
    initial
    begin
        $dumpfile("tb.vcd");
        $dumpvars(0, tb);
    end

    reg [0:7] Red, Green, Blue;
    reg clk;
    wire [0:7] RedOut, GreenOut, BlueOut;

    RGBtoGrayscale uut(Red, Green, Blue, RedOut, GreenOut, BlueOut, clk);
    always #5 clk = ~clk;

    initial
    begin
        clk <= 1'b1;
        #5;
        for (Red = 0; Red <= 240; Red = Red + 10)
        begin
            for (Blue = 0; Blue <= 240; Blue = Blue + 10)
            begin
                for (Green = 0; Green <= 240; Green = Green + 10)
                repeat (2) @(posedge clk);
            end
        end
        $finish;
    end
endmodule

tb.vcd
$date
	Thu May 13 16:22:00 2021
$end
$version
	Icarus Verilog
$end
$timescale
	1ns
$end
$scope module tb $end
$var wire 8 ! RedOut [0:7] $end
$var wire 8 " GreenOut [0:7] $end
$var wire 8 # BlueOut [0:7] $end
$var reg 8 $ Blue [0:7] $end
$var reg 8 % Green [0:7] $end
$var reg 8 & Red [0:7] $end
$var reg 1 ' clk $end
$scope module uut $end
$var wire 8 ( Blue [0:7] $end
$var wire 8 ) Green [0:7] $end
$var wire 8 * Red [0:7] $end
$var wire 1 ' clk $end
$var reg 8 + BlueOut [0:7] $end
$var reg 8 , GrayValue [0:7] $end
$var reg 8 - GreenOut [0:7] $end
$var reg 8 . RedOut [0:7] $end
$upscope $end
$upscope $end
$enddefinitions $end
#0
$dumpvars
bx .
bx -
bx ,
bx +
bx *
bx )
bx (
1'
bx &
bx %
bx $
bx #
bx "
bx !
$end
#5
b0 "
b0 -
b0 #
b0 +
b0 !
b0 .
b0 ,
b0 %
b0 )
b0 $
b0 (
b0 &
b0 *
0'
#10
1'
#15
0'
#20
b1010 %
b1010 )
1'
#25
b110 "
b110 -
b110 #
b110 +
b110 !
b110 .
b110 ,
0'
#30
1'
#35
0'
#40
b10100 %
b10100 )
1'
#45
b1100 "
b1100 -
b1100 #
b1100 +
b1100 !
b1100 .
b1100 ,
0'
#50
1'
#55
0'
#60
b11110 %
b11110 )
1'
#65
b10010 "
b10010 -
b10010 #
b10010 +
b10010 !
b10010 .
b10010 ,
0'
#70
1'
#75
0'
#80
b101000 %
b101000 )
1'
#85
b11000 "
b11000 -
b11000 #
b11000 +
b11000 !
b11000 .
b11000 ,
0'
#90
1'
#95
0'
#100
b110010 %
b110010 )
1'
#105
b11110 "
b11110 -
b11110 #
b11110 +
b11110 !
b11110 .
b11110 ,
0'
#110
1'
#115
0'
#120
b111100 %
b111100 )
1'
#125
b100011 "
b100011 -
b100011 #
b100011 +
b100011 !
b100011 .
b100011 ,
0'
#130
1'
#135
0'
#140
b1000110 %
b1000110 )
1'
#145
b101001 "
b101001 -
b101001 #
b101001 +
b101001 !
b101001 .
b101001 ,
0'
#150
1'
#155
0'
#160
b1010000 %
b1010000 )
1'
#165
b101111 "
b101111 -
b101111 #
b101111 +
b101111 !
b101111 .
b101111 ,
0'
#170
1'
#175
0'
#180
b1011010 %
b1011010 )
1'
#185
b110101 "
b110101 -
b110101 #
b110101 +
b110101 !
b110101 .
b110101 ,
0'
#190
1'
#195
0'
#200
b1100100 %
b1100100 )
1'
#205
b111011 "
b111011 -
b111011 #
b111011 +
b111011 !
b111011 .
b111011 ,
0'
#210
1'
#215
0'
#220
b1101110 %
b1101110 )
1'
#225
b1000001 "
b1000001 -
b1000001 #
b1000001 +
b1000001 !
b1000001 .
b1000001 ,
0'
#230
1'
#235
0'
#240
b1111000 %
b1111000 )
1'
#245
b1000111 "
b1000111 -
b1000111 #
b1000111 +
b1000111 !
b1000111 .
b1000111 ,
0'
#250
1'
#255
0'
#260
b10000010 %
b10000010 )
1'
#265
b1001101 "
b1001101 -
b1001101 #
b1001101 +
b1001101 !
b1001101 .
b1001101 ,
0'
#270
1'
#275
0'
#280
b10001100 %
b10001100 )
1'
#285
b1010011 "
b1010011 -
b1010011 #
b1010011 +
b1010011 !
b1010011 .
b1010011 ,
0'
#290
1'
#295
0'
#300
b10010110 %
b10010110 )
1'
#305
b1011001 "
b1011001 -
b1011001 #
b1011001 +
b1011001 !
b1011001 .
b1011001 ,
0'
#310
1'
#315
0'
#320
b10100000 %
b10100000 )
1'
#325
b1011110 "
b1011110 -
b1011110 #
b1011110 +
b1011110 !
b1011110 .
b1011110 ,
0'
#330
1'
#335
0'
#340
b10101010 %
b10101010 )
1'
#345
b1100100 "
b1100100 -
b1100100 #
b1100100 +
b1100100 !
b1100100 .
b1100100 ,
0'
#350
1'
#355
0'
#360
b10110100 %
b10110100 )
1'
#365
b1101010 "
b1101010 -
b1101010 #
b1101010 +
b1101010 !
b1101010 .
b1101010 ,
0'
#370
1'
#375
0'
#380
b10111110 %
b10111110 )
1'
#385
b1110000 "
b1110000 -
b1110000 #
b1110000 +
b1110000 !
b1110000 .
b1110000 ,
0'
#390
1'
#395
0'
#400
b11001000 %
b11001000 )
1'
#405
b1110110 "
b1110110 -
b1110110 #
b1110110 +
b1110110 !
b1110110 .
b1110110 ,
0'
#410
1'
#415
0'
#420
b11010010 %
b11010010 )
1'
#425
b1111100 "
b1111100 -
b1111100 #
b1111100 +
b1111100 !
b1111100 .
b1111100 ,
0'
#430
1'
#435
0'
#440
b11011100 %
b11011100 )
1'
#445
b10000010 "
b10000010 -
b10000010 #
b10000010 +
b10000010 !
b10000010 .
b10000010 ,
0'
#450
1'
#455
0'
#460
b11100110 %
b11100110 )
1'
#465
b10001000 "
b10001000 -
b10001000 #
b10001000 +
b10001000 !
b10001000 .
b10001000 ,
0'
#470
1'
#475
0'
#480
b11110000 %
b11110000 )
1'
#485
b10001110 "
b10001110 -
b10001110 #
b10001110 +
b10001110 !
b10001110 .
b10001110 ,
0'
#490
1'
#495
0'
#500
b1010 $
b1010 (
b0 %
b0 )
1'
#505
b1 "
b1 -
b1 #
b1 +
b1 !
b1 .
b1 ,
0'
#510
1'
#515
0'
#520
b1010 %
b1010 )
1'
#525
b111 "
b111 -
b111 #
b111 +
b111 !
b111 .
b111 ,
0'
#530
1'
#535
0'
#540
b10100 %
b10100 )
1'
#545
b1101 "
b1101 -
b1101 #
b1101 +
b1101 !
b1101 .
b1101 ,
0'
#550
1'
#555
0'
#560
b11110 %
b11110 )
1'
#565
b10011 "
b10011 -
b10011 #
b10011 +
b10011 !
b10011 .
b10011 ,
0'
#570
1'
#575
0'
#580
b101000 %
b101000 )
1'
#585
b11001 "
b11001 -
b11001 #
b11001 +
b11001 !
b11001 .
b11001 ,
0'
#590
1'
#595
0'
#600
b110010 %
b110010 )
1'
#605
b11111 "
b11111 -
b11111 #
b11111 +
b11111 !
b11111 .
b11111 ,
0'
#610
1'
#615
0'
#620
b111100 %
b111100 )
1'
#625
b100101 "
b100101 -
b100101 #
b100101 +
b100101 !
b100101 .
b100101 ,
0'
#630
1'
#635
0'
#640
b1000110 %
b1000110 )
1'
#645
b101010 "
b101010 -
b101010 #
b101010 +
b101010 !
b101010 .
b101010 ,
0'
#650
1'
#655
0'
#660
b1010000 %
b1010000 )
1'
#665
b110000 "
b110000 -
b110000 #
b110000 +
b110000 !
b110000 .
b110000 ,
0'
#670
1'
#675
0'
#680
b1011010 %
b1011010 )
1'
#685
b110110 "
b110110 -
b110110 #
b110110 +
b110110 !
b110110 .
b110110 ,
0'
#690
1'
#695
0'
#700
b1100100 %
b1100100 )
1'
#705
b111100 "
b111100 -
b111100 #
b111100 +
b111100 !
b111100 .
b111100 ,
0'
#710
1'
#715
0'
#720
b1101110 %
b1101110 )
1'
#725
b1000010 "
b1000010 -
b1000010 #
b1000010 +
b1000010 !
b1000010 .
b1000010 ,
0'
#730
1'
#735
0'
#740
b1111000 %
b1111000 )
1'
#745
b1001000 "
b1001000 -
b1001000 #
b1001000 +
b1001000 !
b1001000 .
b1001000 ,
0'
#750
1'
#755
0'
#760
b10000010 %
b10000010 )
1'
#765
b1001110 "
b1001110 -
b1001110 #
b1001110 +
b1001110 !
b1001110 .
b1001110 ,
0'
#770
1'
#775
0'
#780
b10001100 %
b10001100 )
1'
#785
b1010100 "
b1010100 -
b1010100 #
b1010100 +
b1010100 !
b1010100 .
b1010100 ,
0'
#790
1'
#795
0'
#800
b10010110 %
b10010110 )
1'
#805
b1011010 "
b1011010 -
b1011010 #
b1011010 +
b1011010 !
b1011010 .
b1011010 ,
0'
#810
1'
#815
0'
#820
b10100000 %
b10100000 )
1'
#825
b1011111 "
b1011111 -
b1011111 #
b1011111 +
b1011111 !
b1011111 .
b1011111 ,
0'
#830
1'
#835
0'
#840
b10101010 %
b10101010 )
1'
#845
b1100101 "
b1100101 -
b1100101 #
b1100101 +
b1100101 !
b1100101 .
b1100101 ,
0'
#850
1'
#855
0'
#860
b10110100 %
b10110100 )
1'
#865
b1101011 "
b1101011 -
b1101011 #
b1101011 +
b1101011 !
b1101011 .
b1101011 ,
0'
#870
1'
#875
0'
#880
b10111110 %
b10111110 )
1'
#885
b1110001 "
b1110001 -
b1110001 #
b1110001 +
b1110001 !
b1110001 .
b1110001 ,
0'
#890
1'
#895
0'
#900
b11001000 %
b11001000 )
1'
#905
b1110111 "
b1110111 -
b1110111 #
b1110111 +
b1110111 !
b1110111 .
b1110111 ,
0'
#910
1'
#915
0'
#920
b11010010 %
b11010010 )
1'
#925
b1111101 "
b1111101 -
b1111101 #
b1111101 +
b1111101 !
b1111101 .
b1111101 ,
0'
#930
1'
#935
0'
#940
b11011100 %
b11011100 )
1'
#945
b10000011 "
b10000011 -
b10000011 #
b10000011 +
b10000011 !
b10000011 .
b10000011 ,
0'
#950
1'
#955
0'
#960
b11100110 %
b11100110 )
1'
#965
b10001001 "
b10001001 -
b10001001 #
b10001001 +
b10001001 !
b10001001 .
b10001001 ,
0'
#970
1'
#975
0'
#980
b11110000 %
b11110000 )
1'
#985
b10001111 "
b10001111 -
b10001111 #
b10001111 +
b10001111 !
b10001111 .
b10001111 ,
0'
#990
1'
#995
0'
#1000
b10100 $
b10100 (
b0 %
b0 )
1'
#1005
b10 "
b10 -
b10 #
b10 +
b10 !
b10 .
b10 ,
0'
#1010
1'
#1015
0'
#1020
b1010 %
b1010 )
1'
#1025
b1000 "
b1000 -
b1000 #
b1000 +
b1000 !
b1000 .
b1000 ,
0'
#1030
1'
#1035
0'
#1040
b10100 %
b10100 )
1'
#1045
b1110 "
b1110 -
b1110 #
b1110 +
b1110 !
b1110 .
b1110 ,
0'
#1050
1'
#1055
0'
#1060
b11110 %
b11110 )
1'
#1065
b10100 "
b10100 -
b10100 #
b10100 +
b10100 !
b10100 .
b10100 ,
0'
#1070
1'
#1075
0'
#1080
b101000 %
b101000 )
1'
#1085
b11010 "
b11010 -
b11010 #
b11010 +
b11010 !
b11010 .
b11010 ,
0'
#1090
1'
#1095
0'
#1100
b110010 %
b110010 )
1'
#1105
b100000 "
b100000 -
b100000 #
b100000 +
b100000 !
b100000 .
b100000 ,
0'
#1110
1'
#1115
0'
#1120
b111100 %
b111100 )
1'
#1125
b100110 "
b100110 -
b100110 #
b100110 +
b100110 !
b100110 .
b100110 ,
0'
#1130
1'
#1135
0'
#1140
b1000110 %
b1000110 )
1'
#1145
b101100 "
b101100 -
b101100 #
b101100 +
b101100 !
b101100 .
b101100 ,
0'
#1150
1'
#1155
0'
#1160
b1010000 %
b1010000 )
1'
#1165
b110001 "
b110001 -
b110001 #
b110001 +
b110001 !
b110001 .
b110001 ,
0'
#1170
1'
#1175
0'
#1180
b1011010 %
b1011010 )
1'
#1185
b110111 "
b110111 -
b110111 #
b110111 +
b110111 !
b110111 .
b110111 ,
0'
#1190
1'
#1195
0'
#1200
b1100100 %
b1100100 )
1'
#1205
b111101 "
b111101 -
b111101 #
b111101 +
b111101 !
b111101 .
b111101 ,
0'
#1210
1'
#1215
0'
#1220
b1101110 %
b1101110 )
1'
#1225
b1000011 "
b1000011 -
b1000011 #
b1000011 +
b1000011 !
b1000011 .
b1000011 ,
0'
#1230
1'
#1235
0'
#1240
b1111000 %
b1111000 )
1'
#1245
b1001001 "
b1001001 -
b1001001 #
b1001001 +
b1001001 !
b1001001 .
b1001001 ,
0'
#1250
1'
#1255
0'
#1260
b10000010 %
b10000010 )
1'
#1265
b1001111 "
b1001111 -
b1001111 #
b1001111 +
b1001111 !
b1001111 .
b1001111 ,
0'
#1270
1'
#1275
0'
#1280
b10001100 %
b10001100 )
1'
#1285
b1010101 "
b1010101 -
b1010101 #
b1010101 +
b1010101 !
b1010101 .
b1010101 ,
0'
#1290
1'
#1295
0'
#1300
b10010110 %
b10010110 )
1'
#1305
b1011011 "
b1011011 -
b1011011 #
b1011011 +
b1011011 !
b1011011 .
b1011011 ,
0'
#1310
1'
#1315
0'
#1320
b10100000 %
b10100000 )
1'
#1325
b1100001 "
b1100001 -
b1100001 #
b1100001 +
b1100001 !
b1100001 .
b1100001 ,
0'
#1330
1'
#1335
0'
#1340
b10101010 %
b10101010 )
1'
#1345
b1100111 "
b1100111 -
b1100111 #
b1100111 +
b1100111 !
b1100111 .
b1100111 ,
0'
#1350
1'
#1355
0'
#1360
b10110100 %
b10110100 )
1'
#1365
b1101100 "
b1101100 -
b1101100 #
b1101100 +
b1101100 !
b1101100 .
b1101100 ,
0'
#1370
1'
#1375
0'
#1380
b10111110 %
b10111110 )
1'
#1385
b1110010 "
b1110010 -
b1110010 #
b1110010 +
b1110010 !
b1110010 .
b1110010 ,
0'
#1390
1'
#1395
0'
#1400
b11001000 %
b11001000 )
1'
#1405
b1111000 "
b1111000 -
b1111000 #
b1111000 +
b1111000 !
b1111000 .
b1111000 ,
0'
#1410
1'
#1415
0'
#1420
b11010010 %
b11010010 )
1'
#1425
b1111110 "
b1111110 -
b1111110 #
b1111110 +
b1111110 !
b1111110 .
b1111110 ,
0'
#1430
1'
#1435
0'
#1440
b11011100 %
b11011100 )
1'
#1445
b10000100 "
b10000100 -
b10000100 #
b10000100 +
b10000100 !
b10000100 .
b10000100 ,
0'
#1450
1'
#1455
0'
#1460
b11100110 %
b11100110 )
1'
#1465
b10001010 "
b10001010 -
b10001010 #
b10001010 +
b10001010 !
b10001010 .
b10001010 ,
0'
#1470
1'
#1475
0'
#1480
b11110000 %
b11110000 )
1'
#1485
b10010000 "
b10010000 -
b10010000 #
b10010000 +
b10010000 !
b10010000 .
b10010000 ,
0'
#1490
1'
#1495
0'
#1500
b11110 $
b11110 (
b0 %
b0 )
1'
#1505
b11 "
b11 -
b11 #
b11 +
b11 !
b11 .
b11 ,
0'
#1510
1'
#1515
0'
#1520
b1010 %
b1010 )
1'
#1525
b1001 "
b1001 -
b1001 #
b1001 +
b1001 !
b1001 .
b1001 ,
0'
#1530
1'
#1535
0'
#1540
b10100 %
b10100 )
1'
#1545
b1111 "
b1111 -
b1111 #
b1111 +
b1111 !
b1111 .
b1111 ,
0'
#1550
1'
#1555
0'
#1560
b11110 %
b11110 )
1'
#1565
b10101 "
b10101 -
b10101 #
b10101 +
b10101 !
b10101 .
b10101 ,
0'
#1570
1'
#1575
0'
#1580
b101000 %
b101000 )
1'
#1585
b11011 "
b11011 -
b11011 #
b11011 +
b11011 !
b11011 .
b11011 ,
0'
#1590
1'
#1595
0'
#1600
b110010 %
b110010 )
1'
#1605
b100001 "
b100001 -
b100001 #
b100001 +
b100001 !
b100001 .
b100001 ,
0'
#1610
1'
#1615
0'
#1620
b111100 %
b111100 )
1'
#1625
b100111 "
b100111 -
b100111 #
b100111 +
b100111 !
b100111 .
b100111 ,
0'
#1630
1'
#1635
0'
#1640
b1000110 %
b1000110 )
1'
#1645
b101101 "
b101101 -
b101101 #
b101101 +
b101101 !
b101101 .
b101101 ,
0'
#1650
1'
#1655
0'
#1660
b1010000 %
b1010000 )
1'
#1665
b110010 "
b110010 -
b110010 #
b110010 +
b110010 !
b110010 .
b110010 ,
0'
#1670
1'
#1675
0'
#1680
b1011010 %
b1011010 )
1'
#1685
b111000 "
b111000 -
b111000 #
b111000 +
b111000 !
b111000 .
b111000 ,
0'
#1690
1'
#1695
0'
#1700
b1100100 %
b1100100 )
1'
#1705
b111110 "
b111110 -
b111110 #
b111110 +
b111110 !
b111110 .
b111110 ,
0'
#1710
1'
#1715
0'
#1720
b1101110 %
b1101110 )
1'
#1725
b1000100 "
b1000100 -
b1000100 #
b1000100 +
b1000100 !
b1000100 .
b1000100 ,
0'
#1730
1'
#1735
0'
#1740
b1111000 %
b1111000 )
1'
#1745
b1001010 "
b1001010 -
b1001010 #
b1001010 +
b1001010 !
b1001010 .
b1001010 ,
0'
#1750
1'
#1755
0'
#1760
b10000010 %
b10000010 )
1'
#1765
b1010000 "
b1010000 -
b1010000 #
b1010000 +
b1010000 !
b1010000 .
b1010000 ,
0'
#1770
1'
#1775
0'
#1780
b10001100 %
b10001100 )
1'
#1785
b1010110 "
b1010110 -
b1010110 #
b1010110 +
b1010110 !
b1010110 .
b1010110 ,
0'
#1790
1'
#1795
0'
#1800
b10010110 %
b10010110 )
1'
#1805
b1011100 "
b1011100 -
b1011100 #
b1011100 +
b1011100 !
b1011100 .
b1011100 ,
0'
#1810
1'
#1815
0'
#1820
b10100000 %
b10100000 )
1'
#1825
b1100010 "
b1100010 -
b1100010 #
b1100010 +
b1100010 !
b1100010 .
b1100010 ,
0'
#1830
1'
#1835
0'
#1840
b10101010 %
b10101010 )
1'
#1845
b1101000 "
b1101000 -
b1101000 #
b1101000 +
b1101000 !
b1101000 .
b1101000 ,
0'
#1850
1'
#1855
0'
#1860
b10110100 %
b10110100 )
1'
#1865
b1101101 "
b1101101 -
b1101101 #
b1101101 +
b1101101 !
b1101101 .
b1101101 ,
0'
#1870
1'
#1875
0'
#1880
b10111110 %
b10111110 )
1'
#1885
b1110011 "
b1110011 -
b1110011 #
b1110011 +
b1110011 !
b1110011 .
b1110011 ,
0'
#1890
1'
#1895
0'
#1900
b11001000 %
b11001000 )
1'
#1905
b1111001 "
b1111001 -
b1111001 #
b1111001 +
b1111001 !
b1111001 .
b1111001 ,
0'
#1910
1'
#1915
0'
#1920
b11010010 %
b11010010 )
1'
#1925
b1111111 "
b1111111 -
b1111111 #
b1111111 +
b1111111 !
b1111111 .
b1111111 ,
0'
#1930
1'
#1935
0'
#1940
b11011100 %
b11011100 )
1'
#1945
b10000101 "
b10000101 -
b10000101 #
b10000101 +
b10000101 !
b10000101 .
b10000101 ,
0'
#1950
1'
#1955
0'
#1960
b11100110 %
b11100110 )
1'
#1965
b10001011 "
b10001011 -
b10001011 #
b10001011 +
b10001011 !
b10001011 .
b10001011 ,
0'
#1970
1'
#1975
0'
#1980
b11110000 %
b11110000 )
1'
#1985
b10010001 "
b10010001 -
b10010001 #
b10010001 +
b10010001 !
b10010001 .
b10010001 ,
0'
#1990
1'
#1995
0'
#2000
b101000 $
b101000 (
b0 %
b0 )
1'
#2005
b100 "
b100 -
b100 #
b100 +
b100 !
b100 .
b100 ,
0'
#2010
1'
#2015
0'
#2020
b1010 %
b1010 )
1'
#2025
b1010 "
b1010 -
b1010 #
b1010 +
b1010 !
b1010 .
b1010 ,
0'
#2030
1'
#2035
0'
#2040
b10100 %
b10100 )
1'
#2045
b10000 "
b10000 -
b10000 #
b10000 +
b10000 !
b10000 .
b10000 ,
0'
#2050
1'
#2055
0'
#2060
b11110 %
b11110 )
1'
#2065
b10110 "
b10110 -
b10110 #
b10110 +
b10110 !
b10110 .
b10110 ,
0'
#2070
1'
#2075
0'
#2080
b101000 %
b101000 )
1'
#2085
b11100 "
b11100 -
b11100 #
b11100 +
b11100 !
b11100 .
b11100 ,
0'
#2090
1'
#2095
0'
#2100
b110010 %
b110010 )
1'
#2105
b100010 "
b100010 -
b100010 #
b100010 +
b100010 !
b100010 .
b100010 ,
0'
#2110
1'
#2115
0'
#2120
b111100 %
b111100 )
1'
#2125
b101000 "
b101000 -
b101000 #
b101000 +
b101000 !
b101000 .
b101000 ,
0'
#2130
1'
#2135
0'
#2140
b1000110 %
b1000110 )
1'
#2145
b101110 "
b101110 -
b101110 #
b101110 +
b101110 !
b101110 .
b101110 ,
0'
#2150
1'
#2155
0'
#2160
b1010000 %
b1010000 )
1'
#2165
b110100 "
b110100 -
b110100 #
b110100 +
b110100 !
b110100 .
b110100 ,
0'
#2170
1'
#2175
0'
#2180
b1011010 %
b1011010 )
1'
#2185
b111001 "
b111001 -
b111001 #
b111001 +
b111001 !
b111001 .
b111001 ,
0'
#2190
1'
#2195
0'
#2200
b1100100 %
b1100100 )
1'
#2205
b111111 "
b111111 -
b111111 #
b111111 +
b111111 !
b111111 .
b111111 ,
0'
#2210
1'
#2215
0'
#2220
b1101110 %
b1101110 )
1'
#2225
b1000101 "
b1000101 -
b1000101 #
b1000101 +
b1000101 !
b1000101 .
b1000101 ,
0'
#2230
1'
#2235
0'
#2240
b1111000 %
b1111000 )
1'
#2245
b1001011 "
b1001011 -
b1001011 #
b1001011 +
b1001011 !
b1001011 .
b1001011 ,
0'
#2250
1'
#2255
0'
#2260
b10000010 %
b10000010 )
1'
#2265
b1010001 "
b1010001 -
b1010001 #
b1010001 +
b1010001 !
b1010001 .
b1010001 ,
0'
#2270
1'
#2275
0'
#2280
b10001100 %
b10001100 )
1'
#2285
b1010111 "
b1010111 -
b1010111 #
b1010111 +
b1010111 !
b1010111 .
b1010111 ,
0'
#2290
1'
#2295
0'
#2300
b10010110 %
b10010110 )
1'
#2305
b1011101 "
b1011101 -
b1011101 #
b1011101 +
b1011101 !
b1011101 .
b1011101 ,
0'
#2310
1'
#2315
0'
#2320
b10100000 %
b10100000 )
1'
#2325
b1100011 "
b1100011 -
b1100011 #
b1100011 +
b1100011 !
b1100011 .
b1100011 ,
0'
#2330
1'
#2335
0'
#2340
b10101010 %
b10101010 )
1'
#2345
b1101001 "
b1101001 -
b1101001 #
b1101001 +
b1101001 !
b1101001 .
b1101001 ,
0'
#2350
1'
#2355
0'
#2360
b10110100 %
b10110100 )
1'
#2365
b1101111 "
b1101111 -
b1101111 #
b1101111 +
b1101111 !
b1101111 .
b1101111 ,
0'
#2370
1'
#2375
0'
#2380
b10111110 %
b10111110 )
1'
#2385
b1110101 "
b1110101 -
b1110101 #
b1110101 +
b1110101 !
b1110101 .
b1110101 ,
0'
#2390
1'
#2395
0'
#2400
b11001000 %
b11001000 )
1'
#2405
b1111010 "
b1111010 -
b1111010 #
b1111010 +
b1111010 !
b1111010 .
b1111010 ,
0'
#2410
1'
#2415
0'
#2420
b11010010 %
b11010010 )
1'
#2425
b10000000 "
b10000000 -
b10000000 #
b10000000 +
b10000000 !
b10000000 .
b10000000 ,
0'
#2430
1'
#2435
0'
#2440
b11011100 %
b11011100 )
1'
#2445
b10000110 "
b10000110 -
b10000110 #
b10000110 +
b10000110 !
b10000110 .
b10000110 ,
0'
#2450
1'
#2455
0'
#2460
b11100110 %
b11100110 )
1'
#2465
b10001100 "
b10001100 -
b10001100 #
b10001100 +
b10001100 !
b10001100 .
b10001100 ,
0'
#2470
1'
#2475
0'
#2480
b11110000 %
b11110000 )
1'
#2485
b10010010 "
b10010010 -
b10010010 #
b10010010 +
b10010010 !
b10010010 .
b10010010 ,
0'
#2490
1'
#2495
0'
#2500
b110010 $
b110010 (
b0 %
b0 )
1'
#2505
b110 "
b110 -
b110 #
b110 +
b110 !
b110 .
b110 ,
0'
#2510
1'
#2515
0'
#2520
b1010 %
b1010 )
1'
#2525
b1011 "
b1011 -
b1011 #
b1011 +
b1011 !
b1011 .
b1011 ,
0'
#2530
1'
#2535
0'
#2540
b10100 %
b10100 )
1'
#2545
b10001 "
b10001 -
b10001 #
b10001 +
b10001 !
b10001 .
b10001 ,
0'
#2550
1'
#2555
0'
#2560
b11110 %
b11110 )
1'
#2565
b10111 "
b10111 -
b10111 #
b10111 +
b10111 !
b10111 .
b10111 ,
0'
#2570
1'
#2575
0'
#2580
b101000 %
b101000 )
1'
#2585
b11101 "
b11101 -
b11101 #
b11101 +
b11101 !
b11101 .
b11101 ,
0'
#2590
1'
#2595
0'
#2600
b110010 %
b110010 )
1'
#2605
b100011 "
b100011 -
b100011 #
b100011 +
b100011 !
b100011 .
b100011 ,
0'
#2610
1'
#2615
0'
#2620
b111100 %
b111100 )
1'
#2625
b101001 "
b101001 -
b101001 #
b101001 +
b101001 !
b101001 .
b101001 ,
0'
#2630
1'
#2635
0'
#2640
b1000110 %
b1000110 )
1'
#2645
b101111 "
b101111 -
b101111 #
b101111 +
b101111 !
b101111 .
b101111 ,
0'
#2650
1'
#2655
0'
#2660
b1010000 %
b1010000 )
1'
#2665
b110101 "
b110101 -
b110101 #
b110101 +
b110101 !
b110101 .
b110101 ,
0'
#2670
1'
#2675
0'
#2680
b1011010 %
b1011010 )
1'
#2685
b111011 "
b111011 -
b111011 #
b111011 +
b111011 !
b111011 .
b111011 ,
0'
#2690
1'
#2695
0'
#2700
b1100100 %
b1100100 )
1'
#2705
b1000001 "
b1000001 -
b1000001 #
b1000001 +
b1000001 !
b1000001 .
b1000001 ,
0'
#2710
1'
#2715
0'
#2720
b1101110 %
b1101110 )
1'
#2725
b1000110 "
b1000110 -
b1000110 #
b1000110 +
b1000110 !
b1000110 .
b1000110 ,
0'
#2730
1'
#2735
0'
#2740
b1111000 %
b1111000 )
1'
#2745
b1001100 "
b1001100 -
b1001100 #
b1001100 +
b1001100 !
b1001100 .
b1001100 ,
0'
#2750
1'
#2755
0'
#2760
b10000010 %
b10000010 )
1'
#2765
b1010010 "
b1010010 -
b1010010 #
b1010010 +
b1010010 !
b1010010 .
b1010010 ,
0'
#2770
1'
#2775
0'
#2780
b10001100 %
b10001100 )
1'
#2785
b1011000 "
b1011000 -
b1011000 #
b1011000 +
b1011000 !
b1011000 .
b1011000 ,
0'
#2790
1'
#2795
0'
#2800
b10010110 %
b10010110 )
1'
#2805
b1011110 "
b1011110 -
b1011110 #
b1011110 +
b1011110 !
b1011110 .
b1011110 ,
0'
#2810
1'
#2815
0'
#2820
b10100000 %
b10100000 )
1'
#2825
b1100100 "
b1100100 -
b1100100 #
b1100100 +
b1100100 !
b1100100 .
b1100100 ,
0'
#2830
1'
#2835
0'
#2840
b10101010 %
b10101010 )
1'
#2845
b1101010 "
b1101010 -
b1101010 #
b1101010 +
b1101010 !
b1101010 .
b1101010 ,
0'
#2850
1'
#2855
0'
#2860
b10110100 %
b10110100 )
1'
#2865
b1110000 "
b1110000 -
b1110000 #
b1110000 +
b1110000 !
b1110000 .
b1110000 ,
0'
#2870
1'
#2875
0'
#2880
b10111110 %
b10111110 )
1'
#2885
b1110110 "
b1110110 -
b1110110 #
b1110110 +
b1110110 !
b1110110 .
b1110110 ,
0'
#2890
1'
#2895
0'
#2900
b11001000 %
b11001000 )
1'
#2905
b1111100 "
b1111100 -
b1111100 #
b1111100 +
b1111100 !
b1111100 .
b1111100 ,
0'
#2910
1'
#2915
0'
#2920
b11010010 %
b11010010 )
1'
#2925
b10000001 "
b10000001 -
b10000001 #
b10000001 +
b10000001 !
b10000001 .
b10000001 ,
0'
#2930
1'
#2935
0'
#2940
b11011100 %
b11011100 )
1'
#2945
b10000111 "
b10000111 -
b10000111 #
b10000111 +
b10000111 !
b10000111 .
b10000111 ,
0'
#2950
1'
#2955
0'
#2960
b11100110 %
b11100110 )
1'
#2965
b10001101 "
b10001101 -
b10001101 #
b10001101 +
b10001101 !
b10001101 .
b10001101 ,
0'
#2970
1'
#2975
0'
#2980
b11110000 %
b11110000 )
1'
#2985
b10010011 "
b10010011 -
b10010011 #
b10010011 +
b10010011 !
b10010011 .
b10010011 ,
0'
#2990
1'
#2995
0'
#3000
b111100 $
b111100 (
b0 %
b0 )
1'
#3005
b111 "
b111 -
b111 #
b111 +
b111 !
b111 .
b111 ,
0'
#3010
1'
#3015
0'
#3020
b1010 %
b1010 )
1'
#3025
b1101 "
b1101 -
b1101 #
b1101 +
b1101 !
b1101 .
b1101 ,
0'
#3030
1'
#3035
0'
#3040
b10100 %
b10100 )
1'
#3045
b10010 "
b10010 -
b10010 #
b10010 +
b10010 !
b10010 .
b10010 ,
0'
#3050
1'
#3055
0'
#3060
b11110 %
b11110 )
1'
#3065
b11000 "
b11000 -
b11000 #
b11000 +
b11000 !
b11000 .
b11000 ,
0'
#3070
1'
#3075
0'
#3080
b101000 %
b101000 )
1'
#3085
b11110 "
b11110 -
b11110 #
b11110 +
b11110 !
b11110 .
b11110 ,
0'
#3090
1'
#3095
0'
#3100
b110010 %
b110010 )
1'
#3105
b100100 "
b100100 -
b100100 #
b100100 +
b100100 !
b100100 .
b100100 ,
0'
#3110
1'
#3115
0'
#3120
b111100 %
b111100 )
1'
#3125
b101010 "
b101010 -
b101010 #
b101010 +
b101010 !
b101010 .
b101010 ,
0'
#3130
1'
#3135
0'
#3140
b1000110 %
b1000110 )
1'
#3145
b110000 "
b110000 -
b110000 #
b110000 +
b110000 !
b110000 .
b110000 ,
0'
#3150
1'
#3155
0'
#3160
b1010000 %
b1010000 )
1'
#3165
b110110 "
b110110 -
b110110 #
b110110 +
b110110 !
b110110 .
b110110 ,
0'
#3170
1'
#3175
0'
#3180
b1011010 %
b1011010 )
1'
#3185
b111100 "
b111100 -
b111100 #
b111100 +
b111100 !
b111100 .
b111100 ,
0'
#3190
1'
#3195
0'
#3200
b1100100 %
b1100100 )
1'
